{
    "configurations": [
        {
            "name": "Mac",
            "includePath": [
                "${workspaceFolder}/**",
                "~/Qt/**",
                "/Users/krishna/Qt/**",
                "/Users/krishna/Qt/QtDesignStudio/Qt Design Studio.app/Contents/Resources/qt6_design_studio_reduced_version/lib/QtWidgets.framework/Versions/A/Headers/**"
            ],
            "defines": [],
            "compilerPath": "/usr/bin/clang",
            "cStandard": "c17",
            "cppStandard": "c++14",
            "intelliSenseMode": "macos-clang-arm64"
        }
    ],
    "version": 4
}